[
  {
    "level1": "专升本",
    "fileName": "2025年云南专升本专项批次vs省控线.pdf",
    "level2": "历年各院校招生专业计划表"
  },
  {
    "level1": "专升本",
    "fileName": "2025年云南专升本普通批次最低分VS省控线.pdf",
    "level2": "历年各院校招生专业计划表"
  },
  {
    "level1": "专升本",
    "fileName": "云南省2024年普通高等学校专升本招生计划、录取分数线.pdf",
    "level2": "历年各院校招生专业计划表"
  },
  {
    "level1": "专升本",
    "fileName": "3500词（分类版）.pdf",
    "level2": "知识板块",
    "level3": "公共英语"
  },
  {
    "level1": "专升本",
    "fileName": "不规则动词变化表.pdf",
    "level2": "知识板块",
    "level3": "公共英语"
  },
  {
    "level1": "专升本",
    "fileName": "专升本英语120个高频词汇编.pdf",
    "level2": "知识板块",
    "level3": "公共英语"
  },
  {
    "level1": "专升本",
    "fileName": "句法基础.pdf",
    "level2": "知识板块",
    "level3": "公共英语"
  },
  {
    "level1": "专升本",
    "fileName": "必备语法句型.pdf",
    "level2": "知识板块",
    "level3": "公共英语"
  },
  {
    "level1": "专升本",
    "fileName": "必背结构短语.pdf",
    "level2": "知识板块",
    "level3": "公共英语"
  },
  {
    "level1": "专升本",
    "fileName": "时态汇总（表格版）.pdf",
    "level2": "知识板块",
    "level3": "公共英语"
  },
  {
    "level1": "专升本",
    "fileName": "核心词汇985个.pdf",
    "level2": "知识板块",
    "level3": "公共英语"
  },
  {
    "level1": "专升本",
    "fileName": "蒙题技巧1.pdf",
    "level2": "知识板块",
    "level3": "公共英语"
  },
  {
    "level1": "专升本",
    "fileName": "蒙题技巧2.pdf",
    "level2": "知识板块",
    "level3": "公共英语"
  },
  {
    "level1": "专升本",
    "fileName": "词法自查清单.pdf",
    "level2": "知识板块",
    "level3": "公共英语"
  },
  {
    "level1": "专升本",
    "fileName": "语法公式100个.pdf",
    "level2": "知识板块",
    "level3": "公共英语"
  },
  {
    "level1": "专升本",
    "fileName": "语法思维导图.pdf",
    "level2": "知识板块",
    "level3": "公共英语"
  },
  {
    "level1": "专升本",
    "fileName": "语法考点总结.pdf",
    "level2": "知识板块",
    "level3": "公共英语"
  },
  {
    "level1": "专升本",
    "fileName": "中国古代文学主要作家流派.pdf",
    "level2": "知识板块",
    "level3": "大学语文"
  },
  {
    "level1": "专升本",
    "fileName": "中国文学史思维导图.pdf",
    "level2": "知识板块",
    "level3": "大学语文"
  },
  {
    "level1": "专升本",
    "fileName": "国内外文学常识考点.pdf",
    "level2": "知识板块",
    "level3": "大学语文"
  },
  {
    "level1": "专升本",
    "fileName": "必备小册子 打印直接背.pdf",
    "level2": "知识板块",
    "level3": "大学语文"
  },
  {
    "level1": "专升本",
    "fileName": "文学常识人物知识点.pdf",
    "level2": "知识板块",
    "level3": "大学语文"
  },
  {
    "level1": "专升本",
    "fileName": "文学常识（元代）.pdf",
    "level2": "知识板块",
    "level3": "大学语文"
  },
  {
    "level1": "专升本",
    "fileName": "文学常识（先秦）.pdf",
    "level2": "知识板块",
    "level3": "大学语文"
  },
  {
    "level1": "专升本",
    "fileName": "文学常识（唐代）.pdf",
    "level2": "知识板块",
    "level3": "大学语文"
  },
  {
    "level1": "专升本",
    "fileName": "文学常识（明代）.pdf",
    "level2": "知识板块",
    "level3": "大学语文"
  },
  {
    "level1": "专升本",
    "fileName": "文学常识（秦汉）.pdf",
    "level2": "知识板块",
    "level3": "大学语文"
  },
  {
    "level1": "专升本",
    "fileName": "文学常识（魏晋南北朝）.pdf",
    "level2": "知识板块",
    "level3": "大学语文"
  },
  {
    "level1": "专升本",
    "fileName": "文常思维导图：元明清人文（全）.pdf",
    "level2": "知识板块",
    "level3": "大学语文"
  },
  {
    "level1": "专升本",
    "fileName": "文常思维导图：先秦人文（全）.pdf",
    "level2": "知识板块",
    "level3": "大学语文"
  },
  {
    "level1": "专升本",
    "fileName": "文常思维导图：宋代人文（全）.pdf",
    "level2": "知识板块",
    "level3": "大学语文"
  },
  {
    "level1": "专升本",
    "fileName": "文常思维导图：魏晋南北朝（全）.pdf",
    "level2": "知识板块",
    "level3": "大学语文"
  },
  {
    "level1": "专升本",
    "fileName": "语文相关常识高频考点.pdf",
    "level2": "知识板块",
    "level3": "大学语文"
  },
  {
    "level1": "专升本",
    "fileName": "专升本高数必备公式300个.pdf",
    "level2": "知识板块",
    "level3": "高等数学"
  },
  {
    "level1": "专升本",
    "fileName": "高数Ⅰ考点汇编（知识点）.pdf",
    "level2": "知识板块",
    "level3": "高等数学"
  },
  {
    "level1": "专升本",
    "fileName": "2020云南专升本真题参考答案.pdf",
    "level2": "近5年真题",
    "level3": "公共英语"
  },
  {
    "level1": "专升本",
    "fileName": "2020云南专升本英语真题.pdf",
    "level2": "近5年真题",
    "level3": "公共英语"
  },
  {
    "level1": "专升本",
    "fileName": "2021云南专升本真题参考答案.pdf",
    "level2": "近5年真题",
    "level3": "公共英语"
  },
  {
    "level1": "专升本",
    "fileName": "2021云南专升本英语真题.pdf",
    "level2": "近5年真题",
    "level3": "公共英语"
  },
  {
    "level1": "专升本",
    "fileName": "2022云南专升本真题参考答案.pdf",
    "level2": "近5年真题",
    "level3": "公共英语"
  },
  {
    "level1": "专升本",
    "fileName": "2022云南专升本英语真题.pdf",
    "level2": "近5年真题",
    "level3": "公共英语"
  },
  {
    "level1": "专升本",
    "fileName": "2023云南专升本真题参考答案.pdf",
    "level2": "近5年真题",
    "level3": "公共英语"
  },
  {
    "level1": "专升本",
    "fileName": "2023云南专升本英语真题.pdf",
    "level2": "近5年真题",
    "level3": "公共英语"
  },
  {
    "level1": "专升本",
    "fileName": "2024云南专升本真题参考答案.pdf",
    "level2": "近5年真题",
    "level3": "公共英语"
  },
  {
    "level1": "专升本",
    "fileName": "2024云南专升本英语真题.pdf",
    "level2": "近5年真题",
    "level3": "公共英语"
  },
  {
    "level1": "专升本",
    "fileName": "2021年云南专升本《语文》真题.pdf",
    "level2": "近5年真题",
    "level3": "大学语文"
  },
  {
    "level1": "专升本",
    "fileName": "2021年云南专升本《语文》答案解析.pdf",
    "level2": "近5年真题",
    "level3": "大学语文"
  },
  {
    "level1": "专升本",
    "fileName": "2022年云南专升本《语文》真题_.pdf",
    "level2": "近5年真题",
    "level3": "大学语文"
  },
  {
    "level1": "专升本",
    "fileName": "2022年云南专升本《语文》答案解析.pdf",
    "level2": "近5年真题",
    "level3": "大学语文"
  },
  {
    "level1": "专升本",
    "fileName": "2023年云南专升本《语文》真题.pdf",
    "level2": "近5年真题",
    "level3": "大学语文"
  },
  {
    "level1": "专升本",
    "fileName": "2023年云南专升本《语文》答案解析.pdf",
    "level2": "近5年真题",
    "level3": "大学语文"
  },
  {
    "level1": "专升本",
    "fileName": "2024年云南专升本《语文》真题.pdf",
    "level2": "近5年真题",
    "level3": "大学语文"
  },
  {
    "level1": "专升本",
    "fileName": "2024年云南专升本《语文》答案解析.pdf",
    "level2": "近5年真题",
    "level3": "大学语文"
  },
  {
    "level1": "专升本",
    "fileName": "2025年云南专升本《语文》真题.pdf",
    "level2": "近5年真题",
    "level3": "大学语文"
  },
  {
    "level1": "专升本",
    "fileName": "2025年云南专升本《语文》答案解析.pdf",
    "level2": "近5年真题",
    "level3": "大学语文"
  },
  {
    "level1": "专升本",
    "fileName": "2021云南专升本高等数学真题卷.pdf",
    "level2": "近5年真题",
    "level3": "高等数学"
  },
  {
    "level1": "专升本",
    "fileName": "2021云南专升本高等数学真题参考答案.pdf",
    "level2": "近5年真题",
    "level3": "高等数学"
  },
  {
    "level1": "专升本",
    "fileName": "2022云南专升本高等数学真题卷.pdf",
    "level2": "近5年真题",
    "level3": "高等数学"
  },
  {
    "level1": "专升本",
    "fileName": "2022云南专升本高等数学真题参考答案.pdf",
    "level2": "近5年真题",
    "level3": "高等数学"
  },
  {
    "level1": "专升本",
    "fileName": "2023云南专升本高等数学真题卷.pdf",
    "level2": "近5年真题",
    "level3": "高等数学"
  },
  {
    "level1": "专升本",
    "fileName": "2023云南专升本高等数学真题参考答案.pdf",
    "level2": "近5年真题",
    "level3": "高等数学"
  },
  {
    "level1": "专升本",
    "fileName": "2024云南专升本高等数学真题卷.pdf",
    "level2": "近5年真题",
    "level3": "高等数学"
  },
  {
    "level1": "专升本",
    "fileName": "2024云南专升本高等数学真题参考答案.pdf",
    "level2": "近5年真题",
    "level3": "高等数学"
  },
  {
    "level1": "专升本",
    "fileName": "2025云南专升本高等数学真题卷.pdf",
    "level2": "近5年真题",
    "level3": "高等数学"
  },
  {
    "level1": "专升本",
    "fileName": "2025云南专升本高等数学真题参考答案.pdf",
    "level2": "近5年真题",
    "level3": "高等数学"
  }
]